README
setup.py
journalism/__init__.py
journalism/columns.py
journalism/exceptions.py
journalism/rows.py
journalism/table.py
journalism.egg-info/PKG-INFO
journalism.egg-info/SOURCES.txt
journalism.egg-info/dependency_links.txt
journalism.egg-info/requires.txt
journalism.egg-info/top_level.txt